acit1515/__init__.py
acit1515/extract.py
acit1515/helpers.py
acit1515/runner.py
acit1515/tests/test.py
acit1515/tests/assignment1/__init__.py
acit1515/tests/assignment1/test_change_grade.py
acit1515/tests/assignment1/test_generate_grade.py
acit1515/tests/assignment1/test_generate_grades.py
acit1515/tests/assignment1/test_get_average.py
acit1515/tests/assignment1/test_get_menu.py
acit1515/tests/assignment1/test_get_status.py
acit1515/tests/assignment1/test_validate_choice.py
acit1515/tests/assignment2/__init__.py
acit1515/tests/assignment2/test_change_grade.py
acit1515/tests/assignment2/test_get_dir.py
acit1515/tests/assignment2/test_get_file_list.py
acit1515/tests/assignment2/test_is_valid_transcript.py
acit1515/tests/assignment2/test_load_transcript.py
acit1515/tests/assignment2/mock/mock.txt
acit1515/tests/assignment2/transcripts/Blank-User.json
acit1515/tests/assignment2/transcripts/Test-User.json
acit1515/tests/assignment2/transcripts/Test-User2.json
acit1515/tests/assignment2/transcripts/User-Test.json
acit1515-1.1.1.dist-info/LICENSE
acit1515-1.1.1.dist-info/METADATA
acit1515-1.1.1.dist-info/WHEEL
acit1515-1.1.1.dist-info/top_level.txt
acit1515-1.1.1.dist-info/RECORD
